drucker/__init__.py
drucker/_project.py
drucker/_version.py
drucker/drucker_dashboard_servicer.py
drucker/drucker_worker.py
drucker/drucker_worker_servicer.py
drucker/logger/__init__.py
drucker/logger/logger_fluent.py
drucker/logger/logger_interface.py
drucker/logger/logger_jsonlogger.py
drucker/models/__init__.py
drucker/models/dao.py
drucker/models/model_assignment.py
drucker/protobuf/__init__.py
drucker/protobuf/drucker_pb2.py
drucker/protobuf/drucker_pb2_grpc.py
drucker/utils/__init__.py
drucker-0.4.5.dist-info/LICENSE
drucker-0.4.5.dist-info/METADATA
drucker-0.4.5.dist-info/WHEEL
drucker-0.4.5.dist-info/top_level.txt
drucker-0.4.5.dist-info/RECORD
