Metadata-Version: 2.1
Name: drucker
Version: 0.4.5
Summary: A Python gRPC framework for serving a machine learning module written in Python.
Home-page: https://github.com/drucker/drucker
Author: Drucker
Author-email: UNKNOWN
License: Apache License Version 2.0
Keywords: Drucker,Kubernetes
Platform: UNKNOWN
Classifier: Development Status :: 3 - Alpha
Classifier: Environment :: Web Environment
Classifier: Topic :: Software Development :: Libraries :: Application Frameworks
Classifier: Intended Audience :: Developers
Classifier: Intended Audience :: Information Technology
Classifier: License :: OSI Approved :: Apache Software License
Classifier: Operating System :: OS Independent
Classifier: Programming Language :: Python
Classifier: Programming Language :: Python :: 3
Classifier: Programming Language :: Python :: 3.6
Classifier: Programming Language :: Python :: 3.7
Requires-Dist: fluent-logger (>=0.9.3)
Requires-Dist: python-json-logger (>=0.1.9)
Requires-Dist: grpcio (>=1.13.0)
Requires-Dist: grpcio-tools (>=1.13.0)
Requires-Dist: PyMySQL (>=0.8.0)
Requires-Dist: SQLAlchemy (>=1.2.7)
Requires-Dist: PyYAML (>=3.12)
